supermage/__init__.py
supermage/__meta__.py
supermage/simulators/__init__.py
supermage/simulators/analytic_cube.py
supermage/simulators/intensity_models.py
supermage/simulators/lensed_cube.py
supermage/simulators/velocity_models.py
supermage/simulators/visibility_cube.py
supermage/solvers/MCMC.py
supermage/solvers/__init__.py
supermage/solvers/optimizers.py
supermage/solvers/swarm_optimization.py
supermage/utils/__init__.py
supermage/utils/angular_distance.py
supermage/utils/doppler_velocities.py
supermage/utils/plotting.py
supermage/utils/primary_beams.py
supermage-0.3.4.dist-info/licenses/LICENSE
supermage-0.3.4.dist-info/METADATA
supermage-0.3.4.dist-info/WHEEL
supermage-0.3.4.dist-info/top_level.txt
supermage-0.3.4.dist-info/RECORD
