Metadata-Version: 2.4
Name: supermage
Version: 0.3.4
Summary: A gas dynamics simulator for galaxies, and so much more.
Home-page: 
Author: Michael James Yantovski Barth
Author-email: mjb299@pitt.edu
License: Unlicense
Classifier: Natural Language :: English
Classifier: Programming Language :: Python
Classifier: Programming Language :: Python :: 3
Classifier: Programming Language :: Python :: 3.8
Classifier: Programming Language :: Python :: 3.9
Classifier: Programming Language :: Python :: 3.10
Classifier: Programming Language :: Python :: 3.11
Classifier: Programming Language :: Python :: 3.12
Requires-Python: >=3.8
License-File: LICENSE
Requires-Dist: astropy
Requires-Dist: caskade
Requires-Dist: caustics
Requires-Dist: graphviz
Requires-Dist: numpy
Requires-Dist: safetensors
Requires-Dist: scipy
Requires-Dist: torch
Requires-Dist: viscube
Dynamic: author
Dynamic: author-email
Dynamic: classifier
Dynamic: description
Dynamic: description-content-type
Dynamic: license
Dynamic: license-file
Dynamic: requires-dist
Dynamic: requires-python
Dynamic: summary
